{"P4": {"labels": ["English"], "postTitle": "\u4e09\u5341\u5929\u82f1\u8bed\u901a\uff08\u4e00\uff09", "postUrl": "post/san-shi-tian-ying-yu-tong-%EF%BC%88-yi-%EF%BC%89.html", "createdDate": "2025-01-22", "dateLabelColor": "#0969da"}, "P2": {"labels": ["documentation"], "postTitle": "\u65e0\u9700\u4ee3\u7406\u4f7f\u7528 Gemini \u7684\u8be6\u7ec6\u64cd\u4f5c\u6b65\u9aa4", "postUrl": "post/wu-xu-dai-li-shi-yong-%20Gemini%20-de-xiang-xi-cao-zuo-bu-zou.html", "createdDate": "2025-01-15", "dateLabelColor": "#0969da"}, "P3": {"labels": ["documentation"], "postTitle": "\u7535\u5f71\u300a\u5f31\u70b9\u300b\u89c2\u540e\u611f", "postUrl": "post/dian-ying-%E3%80%8A-ruo-dian-%E3%80%8B-guan-hou-gan.html", "createdDate": "2014-09-01", "dateLabelColor": "#1f883d"}, "labelColorDict": {"bug": "#d73a4a", "documentation": "#0075ca", "duplicate": "#cfd3d7", "English": "#5319E7", "enhancement": "#a2eeef", "good first issue": "#7057ff", "help wanted": "#008672", "invalid": "#e4e669", "question": "#d876e3", "wontfix": "#ffffff"}}